MANIFEST.in
pyproject.toml
setup.py
py3dtf/__init__.py
py3dtf/gholke_utils.py
py3dtf/transforms.py
py3dtf.egg-info/PKG-INFO
py3dtf.egg-info/SOURCES.txt
py3dtf.egg-info/dependency_links.txt
py3dtf.egg-info/requires.txt
py3dtf.egg-info/top_level.txt